{
  "generated_at": "2026-07-02T20:21:09.420877+00:00",
  "subreddits": [
    "aktier",
    "investingsweden",
    "investing",
    "stocks",
    "StockMarket",
    "wallstreetbets"
  ],
  "placera_companies": [],
  "flashback_forum": "https://www.flashback.org/f487-aktier-60504",
  "allaaktier_source": "https://allaaktier.se/",
  "allaaktier_hot": [
    {
      "ticker": "36-GROUP",
      "company_name": "36 Group",
      "trend7d": 18.9,
      "discord_members": 231,
      "facebook_members": null,
      "market_cap": 9068354.0,
      "owner_count": 482,
      "detail_url": "https://allaaktier.se/bolag/36-group"
    },
    {
      "ticker": "FREEMELT",
      "company_name": "Freemelt",
      "trend7d": 8.25,
      "discord_members": 548,
      "facebook_members": 52,
      "market_cap": 470199389.0,
      "owner_count": 1081,
      "detail_url": "https://allaaktier.se/bolag/freemelt"
    },
    {
      "ticker": "ALZECURE-PHARMA",
      "company_name": "AlzeCure Pharma",
      "trend7d": 7.54,
      "discord_members": 259,
      "facebook_members": 12,
      "market_cap": 934944006.0,
      "owner_count": 970,
      "detail_url": "https://allaaktier.se/bolag/alzecure-pharma"
    },
    {
      "ticker": "ORTOMA",
      "company_name": "Ortoma",
      "trend7d": 5.28,
      "discord_members": 131,
      "facebook_members": null,
      "market_cap": 404700561.0,
      "owner_count": 425,
      "detail_url": "https://allaaktier.se/bolag/ortoma"
    },
    {
      "ticker": "SUBGEN-AI",
      "company_name": "Subgen AI",
      "trend7d": 3.3,
      "discord_members": 808,
      "facebook_members": 2821,
      "market_cap": 106736483.0,
      "owner_count": 1857,
      "detail_url": "https://allaaktier.se/bolag/subgen-ai"
    },
    {
      "ticker": "K33",
      "company_name": "K33",
      "trend7d": 3.28,
      "discord_members": 1068,
      "facebook_members": 1928,
      "market_cap": 443144545.0,
      "owner_count": 6499,
      "detail_url": "https://allaaktier.se/bolag/k33"
    },
    {
      "ticker": "ACUCORT",
      "company_name": "AcuCort",
      "trend7d": 3.08,
      "discord_members": 100,
      "facebook_members": null,
      "market_cap": 139728941.0,
      "owner_count": 363,
      "detail_url": "https://allaaktier.se/bolag/acucort"
    },
    {
      "ticker": "LEADING-EDGE-MATERIALS",
      "company_name": "Leading Edge Materials",
      "trend7d": 2.95,
      "discord_members": 685,
      "facebook_members": null,
      "market_cap": 533088029.0,
      "owner_count": 550,
      "detail_url": "https://allaaktier.se/bolag/leading-edge-materials"
    },
    {
      "ticker": "TRUECALLER",
      "company_name": "Truecaller",
      "trend7d": 1.98,
      "discord_members": 625,
      "facebook_members": null,
      "market_cap": 5221369349.0,
      "owner_count": 3150,
      "detail_url": "https://allaaktier.se/bolag/truecaller"
    },
    {
      "ticker": "BEAMMWAVE",
      "company_name": "BeammWave",
      "trend7d": 1.55,
      "discord_members": 1383,
      "facebook_members": null,
      "market_cap": 750827424.0,
      "owner_count": 766,
      "detail_url": "https://allaaktier.se/bolag/beammwave"
    },
    {
      "ticker": "ASCELIA-PHARMA",
      "company_name": "Ascelia Pharma",
      "trend7d": 1.51,
      "discord_members": 1463,
      "facebook_members": 477,
      "market_cap": 400343507.0,
      "owner_count": 1419,
      "detail_url": "https://allaaktier.se/bolag/ascelia-pharma"
    },
    {
      "ticker": "HUNTER-CAPITAL",
      "company_name": "Hunter Capital",
      "trend7d": 1.5,
      "discord_members": 85,
      "facebook_members": null,
      "market_cap": 45314190.0,
      "owner_count": 147,
      "detail_url": "https://allaaktier.se/bolag/hunter-capital"
    },
    {
      "ticker": "JONDETECH-SENSORS",
      "company_name": "JonDeTech Sensors",
      "trend7d": 1.45,
      "discord_members": 451,
      "facebook_members": null,
      "market_cap": 50655812.0,
      "owner_count": 712,
      "detail_url": "https://allaaktier.se/bolag/jondetech-sensors"
    },
    {
      "ticker": "SMART-EYE",
      "company_name": "Smart Eye",
      "trend7d": 1.41,
      "discord_members": 1507,
      "facebook_members": null,
      "market_cap": 3596486414.0,
      "owner_count": 6897,
      "detail_url": "https://allaaktier.se/bolag/smart-eye"
    },
    {
      "ticker": "GRUVAKTIEBOLAGET-VISCARIA",
      "company_name": "Gruvaktiebolaget Viscaria",
      "trend7d": 1.33,
      "discord_members": 1116,
      "facebook_members": 3706,
      "market_cap": 4787225594.0,
      "owner_count": 3620,
      "detail_url": "https://allaaktier.se/bolag/gruvaktiebolaget-viscaria"
    },
    {
      "ticker": "MOVEBYBIKE",
      "company_name": "MoveByBike",
      "trend7d": 1.32,
      "discord_members": 61,
      "facebook_members": null,
      "market_cap": 35858598.0,
      "owner_count": 1022,
      "detail_url": "https://allaaktier.se/bolag/movebybike"
    },
    {
      "ticker": "KINDA-BRAVE-ENTERTAINMENT",
      "company_name": "Kinda Brave Entertainment",
      "trend7d": 1.28,
      "discord_members": 343,
      "facebook_members": null,
      "market_cap": 124378192.0,
      "owner_count": 622,
      "detail_url": "https://allaaktier.se/bolag/kinda-brave-entertainment"
    },
    {
      "ticker": "LOHILO-FOODS",
      "company_name": "Lohilo Foods",
      "trend7d": 1.19,
      "discord_members": 31,
      "facebook_members": 222,
      "market_cap": 80987210.0,
      "owner_count": 733,
      "detail_url": "https://allaaktier.se/bolag/lohilo-foods"
    },
    {
      "ticker": "CRETURNER-GROUP",
      "company_name": "Creturner Group",
      "trend7d": 1.18,
      "discord_members": 553,
      "facebook_members": 656,
      "market_cap": 13556193.0,
      "owner_count": 435,
      "detail_url": "https://allaaktier.se/bolag/creturner-group"
    },
    {
      "ticker": "DICOT-PHARMA",
      "company_name": "Dicot Pharma",
      "trend7d": 1.16,
      "discord_members": 1164,
      "facebook_members": 297,
      "market_cap": 752705563.0,
      "owner_count": 2374,
      "detail_url": "https://allaaktier.se/bolag/dicot-pharma"
    },
    {
      "ticker": "EATGOOD",
      "company_name": "EatGood",
      "trend7d": 1.14,
      "discord_members": 72,
      "facebook_members": null,
      "market_cap": 5049448.0,
      "owner_count": 218,
      "detail_url": "https://allaaktier.se/bolag/eatgood"
    },
    {
      "ticker": "SIVERS-SEMICONDUCTORS",
      "company_name": "Sivers Semiconductors",
      "trend7d": 1.11,
      "discord_members": 2526,
      "facebook_members": 2874,
      "market_cap": 17405474317.0,
      "owner_count": 5627,
      "detail_url": "https://allaaktier.se/bolag/sivers-semiconductors"
    },
    {
      "ticker": "FLEXQUBE",
      "company_name": "FlexQube",
      "trend7d": 0.88,
      "discord_members": 106,
      "facebook_members": null,
      "market_cap": 509722656.0,
      "owner_count": 272,
      "detail_url": "https://allaaktier.se/bolag/flexqube"
    },
    {
      "ticker": "KLIMATOR",
      "company_name": "Klimator",
      "trend7d": 0.88,
      "discord_members": 39,
      "facebook_members": null,
      "market_cap": 134984272.0,
      "owner_count": 142,
      "detail_url": "https://allaaktier.se/bolag/klimator"
    },
    {
      "ticker": "NYAB",
      "company_name": "NYAB",
      "trend7d": 0.87,
      "discord_members": 205,
      "facebook_members": null,
      "market_cap": 4228048537.0,
      "owner_count": 1730,
      "detail_url": "https://allaaktier.se/bolag/nyab"
    },
    {
      "ticker": "IRLAB-THERAPEUTICS",
      "company_name": "IRLAB Therapeutics",
      "trend7d": 0.81,
      "discord_members": 517,
      "facebook_members": 363,
      "market_cap": 191838378.0,
      "owner_count": 423,
      "detail_url": "https://allaaktier.se/bolag/irlab-therapeutics"
    },
    {
      "ticker": "OBSERVIT",
      "company_name": "Observit",
      "trend7d": 0.77,
      "discord_members": 44,
      "facebook_members": null,
      "market_cap": 349805500.0,
      "owner_count": 1346,
      "detail_url": "https://allaaktier.se/bolag/observit"
    },
    {
      "ticker": "KINNEVIK",
      "company_name": "Kinnevik",
      "trend7d": 0.73,
      "discord_members": 154,
      "facebook_members": null,
      "market_cap": 15253680699.0,
      "owner_count": 14190,
      "detail_url": "https://allaaktier.se/bolag/kinnevik"
    },
    {
      "ticker": "FERROAMP",
      "company_name": "Ferroamp",
      "trend7d": 0.72,
      "discord_members": 49,
      "facebook_members": null,
      "market_cap": 320450211.0,
      "owner_count": 1018,
      "detail_url": "https://allaaktier.se/bolag/ferroamp"
    },
    {
      "ticker": "ONLINE-BRANDS-NORDIC",
      "company_name": "Online Brands Nordic",
      "trend7d": 0.71,
      "discord_members": 94,
      "facebook_members": null,
      "market_cap": 321819551.0,
      "owner_count": 275,
      "detail_url": "https://allaaktier.se/bolag/online-brands-nordic"
    },
    {
      "ticker": "BIOEXTRAX",
      "company_name": "Bioextrax",
      "trend7d": 0.68,
      "discord_members": 854,
      "facebook_members": 280,
      "market_cap": 128048659.0,
      "owner_count": 566,
      "detail_url": "https://allaaktier.se/bolag/bioextrax"
    },
    {
      "ticker": "BRILLIANT-FUTURE",
      "company_name": "Brilliant Future",
      "trend7d": 0.65,
      "discord_members": null,
      "facebook_members": null,
      "market_cap": 53792548.0,
      "owner_count": 90,
      "detail_url": "https://allaaktier.se/bolag/brilliant-future"
    },
    {
      "ticker": "CLINICAL-LASERTHERMIA-SYSTEMS",
      "company_name": "Clinical Laserthermia Systems",
      "trend7d": 0.62,
      "discord_members": 753,
      "facebook_members": 703,
      "market_cap": 106745584.0,
      "owner_count": 882,
      "detail_url": "https://allaaktier.se/bolag/clinical-laserthermia-systems"
    },
    {
      "ticker": "CLOETTA",
      "company_name": "Cloetta",
      "trend7d": 0.59,
      "discord_members": 46,
      "facebook_members": null,
      "market_cap": 14849462934.0,
      "owner_count": 5240,
      "detail_url": "https://allaaktier.se/bolag/cloetta"
    },
    {
      "ticker": "ICONOVO",
      "company_name": "Iconovo",
      "trend7d": 0.59,
      "discord_members": 70,
      "facebook_members": 43,
      "market_cap": 95979572.0,
      "owner_count": 263,
      "detail_url": "https://allaaktier.se/bolag/iconovo"
    },
    {
      "ticker": "APR-TECHNOLOGIES",
      "company_name": "APR Technologies",
      "trend7d": 0.58,
      "discord_members": 166,
      "facebook_members": null,
      "market_cap": 746591472.0,
      "owner_count": 174,
      "detail_url": "https://allaaktier.se/bolag/apr-technologies"
    },
    {
      "ticker": "HACKSAW",
      "company_name": "Hacksaw",
      "trend7d": 0.55,
      "discord_members": 233,
      "facebook_members": null,
      "market_cap": 22484987989.0,
      "owner_count": 3875,
      "detail_url": "https://allaaktier.se/bolag/hacksaw"
    },
    {
      "ticker": "ALZINOVA",
      "company_name": "Alzinova",
      "trend7d": 0.53,
      "discord_members": 568,
      "facebook_members": null,
      "market_cap": 102130841.0,
      "owner_count": 758,
      "detail_url": "https://allaaktier.se/bolag/alzinova"
    },
    {
      "ticker": "FRAGBITE",
      "company_name": "Fragbite",
      "trend7d": 0.5,
      "discord_members": 158,
      "facebook_members": 20,
      "market_cap": 37073632.0,
      "owner_count": 358,
      "detail_url": "https://allaaktier.se/bolag/fragbite"
    },
    {
      "ticker": "KLARNA",
      "company_name": "Klarna",
      "trend7d": 0.48,
      "discord_members": 64,
      "facebook_members": null,
      "market_cap": 75060938606.22,
      "owner_count": 5848,
      "detail_url": "https://allaaktier.se/bolag/klarna"
    },
    {
      "ticker": "CLEAN-MOTION",
      "company_name": "Clean Motion",
      "trend7d": 0.48,
      "discord_members": 269,
      "facebook_members": 250,
      "market_cap": 23373065.0,
      "owner_count": 598,
      "detail_url": "https://allaaktier.se/bolag/clean-motion"
    },
    {
      "ticker": "XER-TECH",
      "company_name": "Xer Tech",
      "trend7d": 0.43,
      "discord_members": 265,
      "facebook_members": null,
      "market_cap": 200389407.0,
      "owner_count": 387,
      "detail_url": "https://allaaktier.se/bolag/xer-tech"
    },
    {
      "ticker": "ACAST",
      "company_name": "Acast",
      "trend7d": 0.41,
      "discord_members": 56,
      "facebook_members": null,
      "market_cap": 7344226715.0,
      "owner_count": 1338,
      "detail_url": "https://allaaktier.se/bolag/acast"
    },
    {
      "ticker": "XMREALITY",
      "company_name": "XMReality",
      "trend7d": 0.37,
      "discord_members": 133,
      "facebook_members": 94,
      "market_cap": 47354918.0,
      "owner_count": 888,
      "detail_url": "https://allaaktier.se/bolag/xmreality"
    },
    {
      "ticker": "FASTIGHETS-AB-BALDER",
      "company_name": "Fastighets AB Balder",
      "trend7d": 0.35,
      "discord_members": 81,
      "facebook_members": null,
      "market_cap": 62332200000.0,
      "owner_count": 3839,
      "detail_url": "https://allaaktier.se/bolag/fastighets-ab-balder"
    },
    {
      "ticker": "RATOS",
      "company_name": "Ratos",
      "trend7d": 0.35,
      "discord_members": 65,
      "facebook_members": null,
      "market_cap": 11077708694.0,
      "owner_count": 595,
      "detail_url": "https://allaaktier.se/bolag/ratos"
    },
    {
      "ticker": "SAAB",
      "company_name": "SAAB",
      "trend7d": 0.33,
      "discord_members": 697,
      "facebook_members": null,
      "market_cap": 292394601083.0,
      "owner_count": 56309,
      "detail_url": "https://allaaktier.se/bolag/saab"
    },
    {
      "ticker": "SOLIDX",
      "company_name": "SolidX",
      "trend7d": 0.32,
      "discord_members": 72,
      "facebook_members": null,
      "market_cap": 89876238.0,
      "owner_count": 216,
      "detail_url": "https://allaaktier.se/bolag/solidx"
    },
    {
      "ticker": "SMOLTEK",
      "company_name": "Smoltek",
      "trend7d": 0.28,
      "discord_members": 2229,
      "facebook_members": 405,
      "market_cap": 524219613.0,
      "owner_count": 2109,
      "detail_url": "https://allaaktier.se/bolag/smoltek"
    },
    {
      "ticker": "SENZIME",
      "company_name": "Senzime",
      "trend7d": 0.26,
      "discord_members": 372,
      "facebook_members": null,
      "market_cap": 668163946.0,
      "owner_count": 505,
      "detail_url": "https://allaaktier.se/bolag/senzime"
    }
  ],
  "twitter_mentions": 0,
  "window_hours": 72,
  "min_mentions": 2,
  "trending": [
    {
      "ticker": "SAAB-B",
      "company_name": "Saab B",
      "sector": "Industrials",
      "discovered": false,
      "mentions": 4,
      "velocity_mentions_per_day": 1.33,
      "avg_sentiment": 0.5,
      "avg_upvote_ratio": 0.5,
      "label": "bullish",
      "trending_score": 2.0,
      "sample_posts": [
        "https://www.flashback.org/sp95307169",
        "https://www.flashback.org/sp95307450",
        "https://www.flashback.org/sp95307536"
      ]
    }
  ],
  "stats": {
    "total_posts_fetched": 67,
    "tickers_with_any_mentions": 1,
    "allaaktier_hot_count": 50,
    "twitter_mentions_count": 0
  }
}